.gitignore
MANIFEST.in
README.md
setup.py
Products/__init__.py
Products.RichDocument.egg-info/PKG-INFO
Products.RichDocument.egg-info/SOURCES.txt
Products.RichDocument.egg-info/dependency_links.txt
Products.RichDocument.egg-info/namespace_packages.txt
Products.RichDocument.egg-info/not-zip-safe
Products.RichDocument.egg-info/requires.txt
Products.RichDocument.egg-info/top_level.txt
Products/RichDocument/__init__.py
Products/RichDocument/config.py
Products/RichDocument/configure.zcml
Products/RichDocument/setuphandlers.py
Products/RichDocument/tinymce.py
Products/RichDocument/version.txt
Products/RichDocument/content/__init__.py
Products/RichDocument/content/attachments.py
Products/RichDocument/content/richdocument.py
Products/RichDocument/i18n/README-I18N.txt
Products/RichDocument/i18n/manual.pot
Products/RichDocument/i18n/rebuild.sh
Products/RichDocument/i18n/richdocument-bg.po
Products/RichDocument/i18n/richdocument-cs.po
Products/RichDocument/i18n/richdocument-da.po
Products/RichDocument/i18n/richdocument-de.po
Products/RichDocument/i18n/richdocument-es.po
Products/RichDocument/i18n/richdocument-fr.po
Products/RichDocument/i18n/richdocument-it.po
Products/RichDocument/i18n/richdocument-plone-bg.po
Products/RichDocument/i18n/richdocument-plone-cs.po
Products/RichDocument/i18n/richdocument-plone-da.po
Products/RichDocument/i18n/richdocument-plone-de.po
Products/RichDocument/i18n/richdocument-plone-es.po
Products/RichDocument/i18n/richdocument-plone-fr.po
Products/RichDocument/i18n/richdocument-plone-it.po
Products/RichDocument/i18n/richdocument-plone-pt-br.po
Products/RichDocument/i18n/richdocument-plone-zh.po
Products/RichDocument/i18n/richdocument-plone.pot
Products/RichDocument/i18n/richdocument-pt-br.po
Products/RichDocument/i18n/richdocument-zh.po
Products/RichDocument/i18n/richdocument.pot
Products/RichDocument/i18n/sync.sh
Products/RichDocument/interfaces/__init__.py
Products/RichDocument/interfaces/richdocument.py
Products/RichDocument/profiles/default/factorytool.xml
Products/RichDocument/profiles/default/import_steps.xml
Products/RichDocument/profiles/default/metadata.xml
Products/RichDocument/profiles/default/propertiestool.xml
Products/RichDocument/profiles/default/richdocument_various.txt
Products/RichDocument/profiles/default/rolemap.xml
