Metadata-Version: 1.1
Name: Products.RichDocument
Version: 3.5.1
Summary: Document type for Plone which allows users to upload images directly into the document during editing
Home-page: http://pypi.python.org/pypi/Products.RichDocument
Author: Martin Aspeli
Author-email: optilude@gmx.net
License: GPL
Keywords: Plone RichDocument attachments images files
Platform: UNKNOWN
Classifier: Development Status :: 5 - Production/Stable
Classifier: Environment :: Web Environment
Classifier: Framework :: Plone
Classifier: License :: OSI Approved :: GNU General Public License (GPL)
Classifier: Operating System :: OS Independent
Classifier: Programming Language :: Python
